LICENSE
README.md
setup.cfg
setup.py
src/pybrake1/__init__.py
src/pybrake1/blocklist_filter.py
src/pybrake1/code_hunks.py
src/pybrake1/git.py
src/pybrake1/global_notifier.py
src/pybrake1/logging.py
src/pybrake1/metrics.py
src/pybrake1/notice.py
src/pybrake1/notifier.py
src/pybrake1/notifier_name.py
src/pybrake1/queries.py
src/pybrake1/queues.py
src/pybrake1/remote_settings.py
src/pybrake1/route_metric.py
src/pybrake1/routes.py
src/pybrake1/settings_data.py
src/pybrake1/tdigest.py
src/pybrake1/utils.py
src/pybrake1/version.py
src/pybrake1.egg-info/PKG-INFO
src/pybrake1.egg-info/SOURCES.txt
src/pybrake1.egg-info/dependency_links.txt
src/pybrake1.egg-info/not-zip-safe
src/pybrake1.egg-info/requires.txt
src/pybrake1.egg-info/top_level.txt
src/pybrake1/middleware/__init__.py
src/pybrake1/middleware/aiohttp.py
src/pybrake1/middleware/celery.py
src/pybrake1/middleware/django.py
src/pybrake1/middleware/flask.py