Metadata-Version: 2.1
Name: pybrake1
Version: 2.0.0
Summary: Python exception notifier for Airbrake
Home-page: http://github.com/airbrake/pybrake
Author: Airbrake Technologies, Inc.
Author-email: support@airbrake.io
License: MIT
Keywords: airbrake exception error notifier
Platform: UNKNOWN
Classifier: Development Status :: 3 - Alpha
Classifier: License :: OSI Approved :: MIT License
Classifier: Programming Language :: Python :: 3.6
Classifier: Programming Language :: Python :: 3.7
Classifier: Programming Language :: Python :: 3.8
Classifier: Programming Language :: Python :: 3.9
Classifier: Programming Language :: Python :: 3.10
Classifier: Topic :: Software Development
License-File: LICENSE
